<?xml version="1.0" encoding="UTF-8"?>
<!DOCTYPE recipeml
  PUBLIC "-//FormatData//DTD RecipeML 0.5//EN" "http://www.formatdata.com/recipeml/recipeml.dtd">
<recipeml version="0.5" xml:lang="fr">
   <recipe>
      <head>
         <title>Tarte aux pommes à l'Alsacienne</title>
         <source>http://www.marmiton.org/</source>
         <yield>
            <qty>6</qty>
            <unit>personnes</unit>
         </yield>
         <preptime type="preparation">
            <time>
               <qty>25</qty>
               <timeunit>minutes</timeunit>
            </time>
         </preptime>
         <preptime type="cooking">
            <time>
               <qty>30</qty>
               <timeunit>minutes</timeunit>
            </time>
         </preptime>
      </head>
      <ingredients>
         <ing optional="no">
            <amt>
               <range>
                  <q1>3</q1>
                  <q2>4</q2>
               </range>
            </amt>
            <item>pommes (selon la grosseur)</item>
         </ing>
         <ing optional="no">
            <amt>
               <qty>1</qty>
            </amt>
            <item>pâte brisée</item>
         </ing>
         <ing optional="no">
            <amt>
               <qty>2</qty>
            </amt>
            <item>oeufs</item>
         </ing>
         <ing optional="no">
            <amt>
               <qty>25</qty>
               <unit>cl</unit>
            </amt>
            <item>de crème fraîche</item>
         </ing>
         <ing optional="no">
            <amt>
               <qty>100</qty>
               <unit>g</unit>
            </amt>
            <item>de  sucre  en poudre</item>
         </ing>
         <ing optional="no">
            <amt>
               <qty>1</qty>
               <unit>sachet</unit>
            </amt>
            <item>de  sucre  vanillé</item>
         </ing>
      </ingredients>
      <directions>
         <step type="cooking" optional="no">Posez sur un fond de moule à tarte une  pâte brisée  que vous trouez avec une fourchette.</step>
         <step type="cooking" optional="no">Pelez et coupez les  pommes  en fines tranches que vous disposer sur le fond de tarte.</step>
         <step type="cooking" optional="no">Dans un saladier, mélangez le  sucre , la crème fraîche, les  oeufs , le  sucre  vanillé; versez le tout sur les  pommes .</step>
         <step type="cooking" optional="no">Enfournez au four préchauffé à 200°C (th 6-7), jusqu'à ce que la tarte prenne une belle couleur dorée.</step>
      </directions>
   </recipe>
</recipeml>
